consulta_clima_package/__init__.py
consulta_clima_package/consulta_clima/__init__.py
consulta_clima_package/consulta_clima/clima_api.py
consulta_clima_package-/__init__.py
consulta_clima_package-/consulta_clima/__init__.py
consulta_clima_package-/consulta_clima/clima_api.py
consulta_clima-0.0.1.dist-info/METADATA
consulta_clima-0.0.1.dist-info/WHEEL
consulta_clima-0.0.1.dist-info/top_level.txt
consulta_clima-0.0.1.dist-info/RECORD
