Metadata-Version: 2.1
Name: consulta-clima
Version: 0.0.1
Summary: Package to consult the current climate of a city
Home-page: https://github.com/cleison0silva/pacote_api_clima.git
Author: Cleison Silva
Author-email: cleisoninfo2013@gmail.com
Requires-Python: >=3.8
